{
	"rating": {
		"max": 10,
		"numRaters": 75,
		"average": "8.2",
		"min": 0
	},
	"subtitle": "",
	"author": [
		"[英]菲利普·普尔曼"
	],
	"pubdate": "2013-11-1",
	"tags": [
		{
			"count": 50,
			"name": "格林童话",
			"title": "格林童话"
		},
		{
			"count": 45,
			"name": "童话",
			"title": "童话"
		},
		{
			"count": 19,
			"name": "外国文学",
			"title": "外国文学"
		},
		{
			"count": 17,
			"name": "英国",
			"title": "英国"
		},
		{
			"count": 16,
			"name": "儿童文学",
			"title": "儿童文学"
		},
		{
			"count": 13,
			"name": "文泽尔",
			"title": "文泽尔"
		},
		{
			"count": 8,
			"name": "普尔曼",
			"title": "普尔曼"
		},
		{
			"count": 6,
			"name": "浦睿",
			"title": "浦睿"
		}
	],
	"origin_title": "Grimm Tales：For Young and Old",
	"image": "https://img3.doubanio.com\/mpic\/s27081376.jpg",
	"binding": "",
	"translator": [
		"文泽尔"
	],
	"catalog": "引言\n青蛙国王\n猫与老鼠凑一家\n离家寻找“害怕”的年轻人\n忠诚的约翰内斯\n十二个兄弟\n小哥哥与小妹妹\n野莴苣\n森林里的三个小矮人\n汉塞尔与格莱特\n三片蛇叶\n渔夫和他的妻子\n勇敢的小裁缝\n灰姑娘\n谜语\n老鼠、鸟儿和香肠\n小红帽\n不来梅的乐师们\n唱歌的骨头\n魔鬼的三根金发\n没有手的女孩\n和小精灵有关的故事\n强盗新郎\n死神教父\n杜松树\n睡美人",
	"pages": "328",
	"images": {
		"small": "https://img3.doubanio.com\/spic\/s27081376.jpg",
		"large": "https://img3.doubanio.com\/lpic\/s27081376.jpg",
		"medium": "https://img3.doubanio.com\/mpic\/s27081376.jpg"
	},
	"alt": "https:\/\/book.douban.com\/subject\/24902816\/",
	"id": "24902816",
	"publisher": "浦睿文化·湖南人民出版社",
	"isbn10": "7543893983",
	"isbn13": "9787543893986",
	"title": "格林童话I",
	"url": "https:\/\/api.douban.com\/v2\/book\/24902816",
	"alt_title": "Grimm Tales：For Young and Old",
	"author_intro": "菲利普•普尔曼（Philip Pullman），当代英国最杰出的作家之一。国际畅销书“黑质三部曲”作者。毕业于牛津大学，曾任教威斯敏斯特学院，教授维多利亚时期文学与民间故事。普尔曼善于讲故事，行文简洁朴素又不失文学深度，其作品曾获“英国国家图书奖”“卡耐基儿童文学奖”英国儿童文学最高奖“卫报小说奖”“林格伦儿童文学奖”等多项大奖。2004年，因其杰出的文学成就，被授予大英帝国勋章（CBE）。2008年，被《泰晤士报》评为“1945年后五十位最伟大的英国作家之一”。",
	"summary": "1812年，格林兄弟的《儿童与家庭童话集》出版。两百年来，它被翻译成无数种语言，在全世界范围内广为传播，成了一切西方童话故事的来源与开端。\n2012年，被誉为“1945年后五十位最伟大的英国作家之一”的菲利普·普尔曼，精选了五十则他最爱的童话，以清澈如水的语调加以重述，构成了《格林童话Ⅰ》和《格林童话Ⅱ》这两本书。我们熟知的《青蛙王子》《睡美人》《白雪公主》，以及那些智慧但陌生的《三片蛇叶》《刺猬汉斯》《死神教父》，在他的笔下都变得更为鲜活生动，更贴近我们当代人的阅读趣味。以后很多年，它都值得我们一遍遍地大声朗读。《纽约时报》赞誉说，“这是属于我们这个时代最完美的格林童话。”\n普尔曼在每则童话后附注了简明有趣的评论，追溯故事的缘起、历史背景，以及流传至今的原因，勾勒出两个世纪以来，人类曾有的想象力和生活形态。",
	"series": {
		"id": "20679",
		"title": "普尔曼重述格林童话"
	},
	"price": "34.00元"
}