{
	"rating": {
		"max": 10,
		"numRaters": 13,
		"average": "7.8",
		"min": 0
	},
	"subtitle": "第3版",
	"author": [
		"[美] Jeffrey E.F.Friedl"
	],
	"pubdate": "2012-7",
	"tags": [
		{
			"count": 13,
			"name": "正则表达式",
			"title": "正则表达式"
		},
		{
			"count": 8,
			"name": "编程",
			"title": "编程"
		},
		{
			"count": 8,
			"name": "计算机",
			"title": "计算机"
		},
		{
			"count": 4,
			"name": "基础",
			"title": "基础"
		},
		{
			"count": 1,
			"name": "DM&BI",
			"title": "DM&BI"
		},
		{
			"count": 1,
			"name": "技术",
			"title": "技术"
		},
		{
			"count": 1,
			"name": "校图",
			"title": "校图"
		},
		{
			"count": 1,
			"name": "程序猿",
			"title": "程序猿"
		}
	],
	"origin_title": "",
	"image": "https://img3.doubanio.com\/mpic\/s11292040.jpg",
	"binding": "平装",
	"translator": [
		"余晟"
	],
	"catalog": "前言\tI\n第1章：正则表达式入门\t1\n解决实际问题\t2\n作为编程语言的正则表达式\t4\n以文件名做类比\t4\n以语言做类比\t5\n正则表达式的思维框架\t6\n对于有部分经验的读者\t6\n检索文本文件：Egrep\t6\nEgrep元字符\t8\n行的起始和结束\t8\n字符组\t9\n用点号匹配任意字符\t11\n多选结构\t13\n忽略大小写\t14\n单词分界符\t15\n小结\t16\n可选项元素\t17\n其他量词：重复出现\t18\n括号及反向引用\t20\n神奇的转义\t22\n基础知识拓展\t23\n语言的差异\t23\n正则表达式的目标\t23\n更多的例子\t23\n正则表达式术语汇总\t27\n改进现状\t30\n总结\t32\n一家之言\t33\n第2章：入门示例拓展\t35\n关于这些例子\t36\nPerl简单入门\t37\n使用正则表达式匹配文本\t38\n向更实用的程序前进\t40\n成功匹配的副作用\t40\n错综复杂的正则表达式\t43\n暂停片刻\t49\n使用正则表达式修改文本\t50\n例子：公函生成程序\t50\n举例：修整股票价格\t51\n自动的编辑操作\t53\n处理邮件的小工具\t53\n用环视功能为数值添加逗号\t59\nText-to-HTML转换\t67\n回到单词重复问题\t77\n第3章：正则表达式的特性和流派概览\t83\n在正则的世界中漫步\t85\n正则表达式的起源\t85\n最初印象\t91\n正则表达式的注意事项和处理方式\t93\n集成式处理\t94\n程序式处理和面向对象式处理\t95\n查找和替换\t98\n其他语言中的查找和替换\t100\n注意事项和处理方式：小结\t101\n字符串，字符编码和匹配模式\t101\n作为正则表达式的字符串\t101\n字符编码\t105\nUnicode\t106\n正则模式和匹配模式\t110\n常用的元字符和特性\t113\n字符表示法\t115\n字符组及相关结构\t118\n锚点及其他“零长度断言”\t129\n注释和模式修饰符\t135\n分组，捕获，条件判断和控制\t137\n高级话题引导\t142\n第4章：表达式的匹配原理\t143\n发动引擎\t143\n两类引擎\t144\n新的标准\t144\n正则引擎的分类\t145\n几句题外话\t146\n测试引擎的类型\t146\n匹配的基础\t147\n关于范例\t147\n规则1：优先选择最左端的匹配结果\t148\n引擎的构造\t149\n规则2：标准量词是匹配优先的\t151\n表达式主导与文本主导\t153\nNFA引擎：表达式主导\t153\nDFA引擎：文本主导\t155\n第一想法：比较NFA与DFA\t156\n回溯\t157\n真实世界中的例子：面包屑\t158\n回溯的两个要点\t159\n备用状态\t159\n回溯与匹配优先\t162\n关于匹配优先和回溯的更多内容\t163\n匹配优先的问题\t164\n多字符“引文”\t165\n使用忽略优先量词\t166\n匹配优先和忽略优先都期望获得匹配\t167\n匹配优先、忽略优先和回溯的要旨\t168\n占有优先量词和固化分组\t169\n占有优先量词，?+、*+、++和{m,n}+\t172\n环视中的回溯\t173\n多选结构也是匹配优先的吗\t174\n发掘有序多选结构的价值\t175\nNFA、DFA和POSIX\t177\n最左最长规则\t177\nPOSIX和最左最长规则\t178\n速度和效率\t179\n小结：NFA与DFA的比较\t180\n总结\t183\n第5章：正则表达式实用技巧\t185\n正则表达式的平衡法则\t186\n若干简单的例子\t186\n匹配连续行（续前）\t186\n匹配IP地址\t187\n处理文件名\t190\n匹配对称的括号\t193\n防备不期望的匹配\t194\n匹配分隔符之内的文本\t196\n了解数据，做出假设\t198\n去除文本首尾的空白字符\t199\nHTML相关范例\t200\n匹配HTML Tag\t200\n匹配HTML Link\t201\n检查HTTP URL\t203\n验证主机名\t203\n在真实世界中提取URL\t206\n扩展的例子\t208\n保持数据的协调性\t209\n解析CSV文件\t213\n第6章：打造高效正则表达式\t221\n典型示例\t222\n稍加修改——先迈最好使的腿\t223\n效率vs准确性\t223\n继续前进——限制匹配优先的作用范围\t225\n实测\t226\n全面考察回溯\t228\nPOSIX NFA需要更多处理\t229\n无法匹配时必须进行的工作\t230\n看清楚一点\t231\n多选结构的代价很高\t231\n性能测试\t232\n理解测量对象\t234\nPHP测试\t234\nJava测试\t235\nVB.NET测试\t237\nRuby测试\t238\nPython测试\t238\nTcl测试\t239\n常见优化措施\t240\n有得必有失\t240\n优化各有不同\t241\n正则表达式的应用原理\t241\n应用之前的优化措施\t242\n通过传动装置进行优化\t246\n优化正则表达式本身\t247\n提高表达式速度的诀窍\t252\n常识性优化\t254\n将文字文本独立出来\t255\n将锚点独立出来\t256\n忽略优先还是匹配优先？具体情况具体分析\t256\n拆分正则表达式\t257\n模拟开头字符识别\t258\n使用固化分组和占有优先量词\t259\n主导引擎的匹配\t260\n消除循环\t261\n方法1：依据经验构建正则表达式\t262\n真正的“消除循环”解法\t264\n方法2：自顶向下的视角\t266\n方法3：匹配主机名\t267\n观察\t268\n使用固化分组和占有优先量词\t268\n简单的消除循环的例子\t270\n消除C语言注释匹配的循环\t272\n流畅运转的表达式\t277\n引导匹配的工具\t277\n引导良好的正则表达式速度很快\t279\n完工\t281\n总结：开动你的大脑\t281\n第7章：Perl\t283\n作为语言组件的正则表达式\t285\nPerl的长处\t286\nPerl的短处\t286\nPerl的正则流派\t286\n正则运算符和正则文字\t288\n正则文字的解析方式\t292\n正则修饰符\t292\n正则表达式相关的Perl教义\t293\n表达式应用场合\t294\n动态作用域及正则匹配效应\t295\n匹配修改的特殊变量\t299\nqr\/…\/运算符与regex对象\t303\n构建和使用regex对象\t303\n探究regex对象\t305\n用regex对象提高效率\t306\nMatch运算符\t306\nMatch的正则运算元\t307\n指定目标运算元\t308\nMatch运算符的不同用途\t309\n迭代匹配：Scalar Context，使用\/g\t312\nMatch运算符与环境的关系\t316\nSubstitution运算符\t318\n运算元replacement\t319\n\/e修饰符\t319\n应用场合与返回值\t321\nSplit运算符\t321\nSplit基础知识\t322\n返回空元素\t324\nSplit中的特殊Regex运算元\t325\nSplit中带捕获型括号的match运算元\t326\n巧用Perl的专有特性\t326\n用动态正则表达式结构匹配嵌套结构\t328\n使用内嵌代码结构\t331\n在内嵌代码结构中使用local函数\t335\n关于内嵌代码和my变量的忠告\t338\n使用内嵌代码匹配嵌套结构\t340\n正则文字重载\t341\n正则文字重载的问题\t344\n模拟命名捕获\t344\n效率\t347\n办法不只一种\t348\n表达式编译、\/o修饰符、qr\/???\/和效率\t348\n理解“原文”副本\t355\nStudy函数\t359\n性能测试\t360\n正则表达式调试信息\t361\n结语\t363\n第8章：Java\t365\nJava的正则流派\t366\nJava对\\p{…}和\\P{…}的支持\t369\nUnicode行终结符\t370\n使用java.util.regex\t371\nThe Pattern.compile() Factory\t372\nPattern的matcher方法\t373\nMatcher对象\t373\n应用正则表达式\t375\n查询匹配结果\t376\n简单查找-替换\t378\n高级查找-替换\t380\n原地查找-替换\t382\nMatcher的检索范围\t384\n方法链\t389\n构建扫描程序\t389\nMatcher的其他方法\t392\nPattern的其他方法\t394\nPattern的split方法，单个参数\t395\nPattern的split方法，两个参数\t396\n拓展示例\t397\n为Image Tag添加宽度和高度属性\t397\n对于每个Matcher，使用多个Pattern校验HTML\t399\n解析CSV文档\t401\nJava版本差异\t401\n1.4.2和1.5.0之间的差异\t402\n1.5.0和1.6之间的差异\t403\n第9章：.NET\t405\n.NET的正则流派\t406\n对于流派的补充\t409\n使用.NET正则表达式\t413\n正则表达式快速入门\t413\n包概览\t415\n核心对象概览\t416\n核心对象详解\t418\n创建Regex对象\t419\n使用Regex对象\t421\n使用Match对象\t427\n使用Group对象\t430\n静态“便捷”函数\t431\n正则表达式缓存\t432\n支持函数\t432\n.NET高级话题\t434\n正则表达式装配件\t434\n匹配嵌套结构\t436\nCapture对象\t437\n第10章：PHP\t439\nPHP的正则流派\t441\nPreg函数接口\t443\n“Pattern”参数\t444\nPreg函数罗列\t449\npreg_match\t449\npreg_match_all\t453\npreg_replace\t458\npreg_replace_callback\t463\npreg_split\t465\npreg_grep\t469\npreg_quote\t470\n“缺失”的preg函数\t471\npreg_regex_to_pattern\t472\n对未知的Pattern参数进行语法检查\t474\n对未知正则表达式进行语法检查\t475\n递归的正则表达式\t475\n匹配嵌套括号内的文本\t475\n不能回溯到递归调用之内\t477\n匹配一组嵌套的括号\t478\n效率\t478\n模式修饰符S：“研究”\t478\n扩展示例\t480\n用PHP解析CSV\t480\n检查tagged data的嵌套正确性\t481\n索引\t485",
	"pages": "515",
	"images": {
		"small": "https://img3.doubanio.com\/spic\/s11292040.jpg",
		"large": "https://img3.doubanio.com\/lpic\/s11292040.jpg",
		"medium": "https://img3.doubanio.com\/mpic\/s11292040.jpg"
	},
	"alt": "https:\/\/book.douban.com\/subject\/11589967\/",
	"id": "11589967",
	"publisher": "电子工业出版社",
	"isbn10": "7121175010",
	"isbn13": "9787121175015",
	"title": "精通正则表达式",
	"url": "https:\/\/api.douban.com\/v2\/book\/11589967",
	"alt_title": "",
	"author_intro": "",
	"summary": "《精通正则表达式(第3版)》内容简介：随着互联网的迅速发展，几乎所有工具软件和程序语言都支持的正则表达式也变得越来越强大和易于使用。《精通正则表达式(第3版)》是讲解正则表达式的经典之作。《精通正则表达式(第3版)》主要讲解了正则表达式的特性和流派、匹配原理、优化原则、实用诀窍以及调校措施，并详细介绍了正则表达式在Perl、Java、.NET、PHP中的用法。《精通正则表达式(第3版)》自第1版开始着力于教会读者“以正则表达式来思考”，来让读者真正“精通”正则表达式。该版对PHP的相关内容、Javal.5和Javal.6的新特性作了可观的扩充讲解。任何有机会仲用正则表达式的读者都会从中获益匪浅。",
	"price": "89.00元"
}