{
	"rating": {
		"max": 10,
		"numRaters": 4,
		"average": "0.0",
		"min": 0
	},
	"subtitle": "原本大学微言",
	"author": [
		"南怀瑾"
	],
	"pubdate": "2013-3",
	"tags": [
		{
			"count": 1,
			"name": "南怀瑾",
			"title": "南怀瑾"
		},
		{
			"count": 1,
			"name": "国学",
			"title": "国学"
		},
		{
			"count": 1,
			"name": "国学国粹经典传承",
			"title": "国学国粹经典传承"
		},
		{
			"count": 1,
			"name": "文学经典",
			"title": "文学经典"
		}
	],
	"origin_title": "",
	"image": "https:\/\/img1.doubanio.com\/mpic\/s26681133.jpg",
	"binding": "精装",
	"translator": [],
	"catalog": "",
	"pages": "506",
	"images": {
		"small": "https:\/\/img1.doubanio.com\/spic\/s26681133.jpg",
		"large": "https:\/\/img1.doubanio.com\/lpic\/s26681133.jpg",
		"medium": "https:\/\/img1.doubanio.com\/mpic\/s26681133.jpg"
	},
	"alt": "http:\/\/book.douban.com\/subject\/22867026\/",
	"id": "22867026",
	"publisher": "",
	"isbn10": "7309094425",
	"isbn13": "9787309094428",
	"title": "南怀瑾选集",
	"url": "http:\/\/api.douban.com\/v2\/book\/22867026",
	"alt_title": "",
	"author_intro": "",
	"summary": "《南怀瑾选集(典藏版)(第11卷)》内容简介：南怀瑾选集典藏版十二卷，是国学泰斗南怀瑾先生（1918-2012）目前为止在中国大陆出版的最权威最全备的作品集。作品集涉及范围，以时空论，乃古今中外。以现代学科分类论，乃文史哲。以传统学术分类论，乃儒释道，实则千门万户，未有不涉及者。南怀瑾选集典藏版十二卷不但是南怀瑾先生在纸面所显现出的渊博如海之学问，有心的每一位读者，更能从中体悟到南先生作为一位大修行人由博返约之深邃面貌。\n众所周知，中国传统文化千门万户，郁郁璨璨，而儒道释实为其纲要。南先生会通三教，群机都摄，尤擅讲论佛法，拈花一脉，绍流如绪，浩浩乎卮言日出，妙义宛然，等身著作，千言万语，一一从智慧海中称性流出，而皆为众人讲说，读其书，想其人，山高水长，人所唱叹。\n癸巳之春，中国大陆有南先生其人其书已二十余载，经台湾老古文化独家授权，《南怀瑾选集》在原来基础上体量扩容为12卷。复旦大学出版社精心审读校对，善为装帧，名之为《南怀瑾选集》典藏版以行世。\n《南怀瑾选集》典藏版各卷收录作品皆为当代学术精华，二十余年来无数读者从中受益。具体书目为：第一卷：《论语别裁》。第二卷：《老子他说》、《孟子旁通》。第三卷：《庄子諵譁》。第四卷：《易经杂说》、《易经系传别讲》。第五卷：《禅宗与道家》、《道家、密宗与东方神秘学》、《静坐修道与长生不老》。第六卷：《禅海蠡测》、《禅话》、《中国佛教发展史略》、《中国道教发展史略》。第七卷：《历史的经验》、《亦新亦旧的一代》、《中国文化泛言》。第八卷：《如何修证佛法》、《药师经的济世观》、《学佛者的基本信念》。第九卷：《金刚经说什么》、《楞严大义今释》。第十卷：《圆觉经略说》、《定慧初修》、《楞伽大义今释》。第十一卷：《原本大学微言》。第十二卷：《南怀瑾讲演录》、《南怀瑾与彼得•圣吉》、《答问青壮年参禅者》、《人生的起点和终站》。\n《南怀瑾选集(典藏版)(第11卷)》：《原本大学微言》，《大学》是儒家的代表作之一，相传为孔子的学生曾子（曾参）所著。它与《中庸》《论语》《孟子》合称“四书”，是宋代以后士人学子必读的教科书。文中以“明明德”、“亲民”、“至善”为纲，“格物、致知、诚意、正心、修身、齐家、治国、平天下”为目，对道德修养与社会政治的关系作了系统的论述，对我国古代的思想文化产生过深远的影响。《原本大学微言》是南怀瑾先生有关《大学》的讲记。书名中说的“原本大学”，指的是《大学》的古本《小戴礼记•大学》。南先生以渊博的学识，综罗大量的文史典故，对《大学》中的微言大义作了揭示，给人以知识的乐趣和人生的启悟。",
	"series": {
		"id": "22376",
		"title": "南怀瑾选集典藏版"
	},
	"price": "69.00元"
}