{
	"rating": {
		"max": 10,
		"numRaters": 903,
		"average": "8.7",
		"min": 0
	},
	"subtitle": "",
	"author": [
		"[美] E·B·怀特"
	],
	"pubdate": "2014-8-1",
	"tags": [
		{
			"count": 195,
			"name": "儿童文学",
			"title": "儿童文学"
		},
		{
			"count": 163,
			"name": "童话",
			"title": "童话"
		},
		{
			"count": 144,
			"name": "温暖",
			"title": "温暖"
		},
		{
			"count": 106,
			"name": "外国文学",
			"title": "外国文学"
		},
		{
			"count": 69,
			"name": "怀特",
			"title": "怀特"
		},
		{
			"count": 67,
			"name": "有趣",
			"title": "有趣"
		},
		{
			"count": 50,
			"name": "法国文学",
			"title": "法国文学"
		},
		{
			"count": 48,
			"name": "小说",
			"title": "小说"
		}
	],
	"origin_title": "",
	"image": "https://img3.doubanio.com\/mpic\/s28332814.jpg",
	"binding": "平装",
	"translator": [
		"任溶溶"
	],
	"catalog": "1.早饭前\n2.小猪威尔伯\n3.逃走\n4.孤独\n5.夏洛\n6.夏日\n7.坏消息\n8.家里的谈话\n9.威尔伯说大话\n10.臭蛋爆炸\n11.奇迹\n12.会议\n13.迸展顺利\n14.多里安医生\n15.蟋蟀\n16.上集市去\n17.叔叔\n18.凉爽的晚上\n19.卵袋\n20.胜利时刻\n21.最后一天\n22.温暖的风",
	"pages": "176",
	"images": {
		"small": "https://img3.doubanio.com\/spic\/s28332814.jpg",
		"large": "https://img3.doubanio.com\/lpic\/s28332814.jpg",
		"medium": "https://img3.doubanio.com\/mpic\/s28332814.jpg"
	},
	"alt": "https:\/\/book.douban.com\/subject\/26278316\/",
	"id": "26278316",
	"publisher": "上海译文出版社",
	"isbn10": "753276737X",
	"isbn13": "9787532767373",
	"title": "夏洛的网",
	"url": "https:\/\/api.douban.com\/v2\/book\/26278316",
	"alt_title": "",
	"author_intro": "E·B·怀特（ E．B．White，1899—1985），“二十世纪最伟大的美国随笔作家和儿童文学家。”作为《纽约客》主要撰稿人的怀特一手奠定了影响深远的“《纽约客》文风”。怀特对这个世界上的一切都充满关爱，他的道德与他的文章一样山高水长。作为儿童文学家，他还为孩子们写了三本享誉世界的童话故事：《精灵鼠小弟》《夏洛的网》《吹小号的天鹅》，它们让大人与孩子同样痴迷，更成为温煦是上无法逾越的文学经典。本书译者为国内著名儿童文学家和翻译家任溶溶先生。",
	"summary": "在朱克曼家的谷仓里，快乐地生活着一群动物，其中小猪威尔伯和蜘蛛夏洛建立了最真挚的友谊。然而，一个最丑陋的消息打破了谷仓的平静：威尔伯未来的命运竟然是成为熏肉火腿。作为一只猪，悲痛绝望的威尔伯似乎只能接受任人宰割的命运，然而，看似渺小的夏洛却说：“我救你。”于是，夏洛用自己的丝在猪栏上织出了被人类视为奇迹的网络文字，并彻底逆转了威尔伯的命运，终于让它在集市的大赛中赢得了特别奖项和一个安享天年的未来。可这时，蜘蛛夏洛的命运却走到了尽头……E·B·怀特用他幽默的大文笔，深入浅出地讲了这个很有哲理意义的故事，关于爱，关于友情，关于生死……",
	"series": {
		"id": "26549",
		"title": "E·B·怀特童话"
	},
	"price": "26.00元"
}